eurekapy/__aws_info_loader.py
eurekapy/__dns_txt_resolver.py
eurekapy/__init__.py
eurekapy/eureka_basic.py
eurekapy/eureka_client.py
eurekapy/http_client.py
eurekapy/logger.py
eurekapy/netint_utils.py
eurekapy-1.0.0.dist-info/LICENSE
eurekapy-1.0.0.dist-info/METADATA
eurekapy-1.0.0.dist-info/WHEEL
eurekapy-1.0.0.dist-info/top_level.txt
eurekapy-1.0.0.dist-info/RECORD
