Metadata-Version: 2.1
Name: eurekapy
Version: 1.0.0
Summary: A eureka client written in python. Support registering your python component to Eureka Server, as well as calling remote services by pulling the the Eureka registry. 
Home-page: UNKNOWN
Author: hexer
Author-email: hexu0614@gmail.com
License: UNKNOWN
Platform: UNKNOWN
Classifier: Programming Language :: Python :: 3.7
Classifier: Programming Language :: Python :: 3.8
Classifier: Programming Language :: Python :: 3.9
Classifier: License :: OSI Approved :: MIT License
Classifier: Operating System :: OS Independent
License-File: LICENSE
Requires-Dist: ifaddr
Requires-Dist: dnspython
